{
    "file": {
        "bucket": "dosm-public-economy",
        "manual_trigger" : "2023-01-09 16:01:30",
        "file_name": "labour-principalstats-monthly",
        "category": "ECONOMY",
        "category_en": "Economy",
        "category_bm": "Ekonomi",
        "subcategory": "LABOUR",
        "subcategory_en": "Labour",
        "subcategory_bm": "Tenaga Buruh",
        "description": {
            "en": "The monthly Labour Force Report presents the statistics of labour force, employment and unemployment obtained from the Labour Force Survey (LFS).",
            "bm": "Laporan Tenaga Buruh bulanan membentangkan statistik berkaitan tenaga buruh, guna tenaga dan pengangguran yang diperoleh daripada Survei Tenaga Buruh (STB). "
        },
        "link_parquet": "https://storage.googleapis.com/dosm-public-economy/labour-principalstats-monthly.parquet",
        "link_csv": "https://storage.googleapis.com/dosm-public-economy/labour-principalstats-monthly.csv",
        "link_metadata": "https://storage.googleapis.com/dosm-public-economy/labour-principalstats-monthly.metadata",
        "variables": [
            {
                "id": -1,
                "name": "date",
                "title_en": "Date",
                "title_bm": "Tarikh",
                "desc_en": "[Date] The date in YYYY-MM-DD format",
                "desc_bm": "[Tarikh] Tarikh dalam format YYYY-MM-DD"
            },
            {
                "id": 1,
                "name": "lf_size",
                "title_en": "Labour Force Size",
                "title_bm": "Tenaga Buruh",
                "desc_en": "[Integer] Variable",
                "desc_bm": "[Integer] Pembolehubah"
            },
            {
                "id": 2,
                "name": "employed",
                "title_en": "Employed Persons",
                "title_bm": "Bekerja",
                "desc_en": "[Integer] Variable",
                "desc_bm": "[Integer] Pembolehubah"
            },
            {
                "id": 3,
                "name": "unemployed",
                "title_en": "Unemployed Persons",
                "title_bm": "Penganggur",
                "desc_en": "[Integer] Variable",
                "desc_bm": "[Integer] Pembolehubah"
            },
            {
                "id": 4,
                "name": "outside",
                "title_en": "Persons Outside Labour Force",
                "title_bm": "Luar Tenaga Buruh",
                "desc_en": "[Integer] Variable",
                "desc_bm": "[Integer] Pembolehubah"
            },
            {
                "id": 5,
                "name": "u_rate",
                "title_en": "Unemployment Rate",
                "title_bm": "Kadar Pengangguran",
                "desc_en": "[Float] Variable",
                "desc_bm": "[Apung] Pembolehubah"
            },
            {
                "id": 6,
                "name": "p_rate",
                "title_en": "Participation Rate",
                "title_bm": "Kadar Penyertaan",
                "desc_en": "[Float] Variable",
                "desc_bm": "[Apung] Pembolehubah"
            },
            {
                "id": 7,
                "name": "ep_ratio",
                "title_en": "Employment-Population Ratio",
                "title_bm": "Nisbah Guna Tenaga kepada Penduduk",
                "desc_en": "[Float] Variable",
                "desc_bm": "[Apung] Pembolehubah"
            },
            {
                "id": 8,
                "name": "lf_size_sa",
                "title_en": "Labour Force Size (sa)",
                "title_bm": "Tenaga Buruh (tsm)",
                "desc_en": "[Integer] Variable",
                "desc_bm": "[Integer] Pembolehubah"
            },
            {
                "id": 9,
                "name": "employed_sa",
                "title_en": "Employed Persons (sa)",
                "title_bm": "Bekerja (tsm)",
                "desc_en": "[Integer] Variable",
                "desc_bm": "[Integer] Pembolehubah"
            },
            {
                "id": 10,
                "name": "unemployed_sa",
                "title_en": "Unemployed Persons (sa)",
                "title_bm": "Penganggur (tsm)",
                "desc_en": "[Integer] Variable",
                "desc_bm": "[Integer] Pembolehubah"
            },
            {
                "id": 11,
                "name": "u_rate_sa",
                "title_en": "Unemployment Rate (sa)",
                "title_bm": "Kadar Pengangguran (tsm)",
                "desc_en": "[Float] Variable",
                "desc_bm": "[Apung] Pembolehubah"
            },
            {
                "id": 12,
                "name": "p_rate_sa",
                "title_en": "Participation Rate (sa)",
                "title_bm": "Kadar Penyertaan (tsm)",
                "desc_en": "[Float] Variable",
                "desc_bm": "[Apung] Pembolehubah"
            },
            {
                "id": 13,
                "name": "unemployed_15_24",
                "title_en": "Unemployed Youths (15-24)",
                "title_bm": "Penganggur Belia (15-24)",
                "desc_en": "[Integer] Variable",
                "desc_bm": "[Integer] Pembolehubah"
            },
            {
                "id": 14,
                "name": "u_rate_15_24",
                "title_en": "Youth Unemployment Rate (15-24)",
                "title_bm": "Kadar Pengangguran Belia (15-24)",
                "desc_en": "[Float] Variable",
                "desc_bm": "[Apung] Pembolehubah"
            },
            {
                "id": 15,
                "name": "unemployed_15_30",
                "title_en": "Unemployed Youths (15-30)",
                "title_bm": "Penganggur Belia (15-30)",
                "desc_en": "[Integer] Variable",
                "desc_bm": "[Integer] Pembolehubah"
            },
            {
                "id": 16,
                "name": "u_rate_15_30",
                "title_en": "Youth Unemployment Rate (15-30)",
                "title_bm": "Kadar Pengangguran Belia (15-30)",
                "desc_en": "[Integer] Variable",
                "desc_bm": "[Integer] Pembolehubah"
            },
            {
                "id": 17,
                "name": "employed_employer",
                "title_en": "Employed Persons: Employers",
                "title_bm": "Bekerja: Majikan",
                "desc_en": "[Integer] Variable",
                "desc_bm": "[Integer] Pembolehubah"
            },
            {
                "id": 18,
                "name": "employed_employee",
                "title_en": "Employed Persons: Employees",
                "title_bm": "Bekerja: Pekerja",
                "desc_en": "[Integer] Variable",
                "desc_bm": "[Integer] Pembolehubah"
            },
            {
                "id": 19,
                "name": "employed_ownaccount",
                "title_en": "Employed Persons: Own-Account Workers",
                "title_bm": "Bekerja: Bekerja Sendiri",
                "desc_en": "[Integer] Variable",
                "desc_bm": "[Integer] Pembolehubah"
            },
            {
                "id": 20,
                "name": "employed_unpaidfamily",
                "title_en": "Employed Persons: Unpaid Family Workers",
                "title_bm": "Bekerja: Pekerja Keluarga Tanpa Gaji",
                "desc_en": "[Integer] Variable",
                "desc_bm": "[Integer] Pembolehubah"
            }
        ]
    },
    "catalog_data": [
        {
            "id": 1,
            "catalog_filters": {
                "frequency": "MONTHLY",
                "geographic": [
                    "NATIONAL"
                ],
                "start": "2010",
                "end": "2022",
                "data_source": [
                    "DOSM"
                ]
            },
            "metadata_neutral": {
                "data_as_of": "2022-10-31 23:59",
                "last_updated": "2022-12-23 12:00",
                "next_update": "2023-01-31 12:00"
            },
            "metadata_lang": {
                "en": {
                    "methodology": "Lorem ipsum dolor sit amet, consectetur adipiscing elit, sed do eiusmod tempor incididunt ut labore et dolore magna aliqua. Ut enim ad minim veniam, quis nostrud exercitation ullamco laboris nisi ut aliquip ex ea commodo consequat.",
                    "caveat": "Lorem ipsum dolor sit amet, consectetur adipiscing elit, sed do eiusmod tempor incididunt ut labore et dolore magna aliqua. Ut enim ad minim veniam, quis nostrud exercitation ullamco laboris nisi ut aliquip ex ea commodo consequat."
                },
                "bm": {
                    "methodology": "Lorem ipsum dolor sit amet, consectetur adipiscing elit, sed do eiusmod tempor incididunt ut labore et dolore magna aliqua. Ut enim ad minim veniam, quis nostrud exercitation ullamco laboris nisi ut aliquip ex ea commodo consequat.",
                    "caveat": "Lorem ipsum dolor sit amet, consectetur adipiscing elit, sed do eiusmod tempor incididunt ut labore et dolore magna aliqua. Ut enim ad minim veniam, quis nostrud exercitation ullamco laboris nisi ut aliquip ex ea commodo consequat."
                }
            },
            "chart": {
                "chart_type": "TIMESERIES",
                "chart_filters": {
                    "SLICE_BY": []
                },
                "chart_variables": {
                    "parents": [],
                    "operation": "MEAN",
                    "format": {
                        "x": "date",
                        "y": "lf_size",
                        "line": ""
                    }
                }
            }
        },
        {
            "id": 2,
            "catalog_filters": {
                "frequency": "MONTHLY",
                "geographic": [
                    "NATIONAL"
                ],
                "start": "2010",
                "end": "2022",
                "data_source": [
                    "DOSM"
                ]
            },
            "metadata_neutral": {
                "data_as_of": "2022-10-31 23:59",
                "last_updated": "2022-12-23 12:00",
                "next_update": "2023-01-31 12:00"
            },
            "metadata_lang": {
                "en": {
                    "methodology": "Lorem ipsum dolor sit amet, consectetur adipiscing elit, sed do eiusmod tempor incididunt ut labore et dolore magna aliqua. Ut enim ad minim veniam, quis nostrud exercitation ullamco laboris nisi ut aliquip ex ea commodo consequat.",
                    "caveat": "Lorem ipsum dolor sit amet, consectetur adipiscing elit, sed do eiusmod tempor incididunt ut labore et dolore magna aliqua. Ut enim ad minim veniam, quis nostrud exercitation ullamco laboris nisi ut aliquip ex ea commodo consequat."
                },
                "bm": {
                    "methodology": "Lorem ipsum dolor sit amet, consectetur adipiscing elit, sed do eiusmod tempor incididunt ut labore et dolore magna aliqua. Ut enim ad minim veniam, quis nostrud exercitation ullamco laboris nisi ut aliquip ex ea commodo consequat.",
                    "caveat": "Lorem ipsum dolor sit amet, consectetur adipiscing elit, sed do eiusmod tempor incididunt ut labore et dolore magna aliqua. Ut enim ad minim veniam, quis nostrud exercitation ullamco laboris nisi ut aliquip ex ea commodo consequat."
                }
            },
            "chart": {
                "chart_type": "TIMESERIES",
                "chart_filters": {
                    "SLICE_BY": []
                },
                "chart_variables": {
                    "parents": [],
                    "operation": "MEAN",
                    "format": {
                        "x": "date",
                        "y": "employed",
                        "line": ""
                    }
                }
            }
        },
        {
            "id": 3,
            "catalog_filters": {
                "frequency": "MONTHLY",
                "geographic": [
                    "NATIONAL"
                ],
                "start": "2010",
                "end": "2022",
                "data_source": [
                    "DOSM"
                ]
            },
            "metadata_neutral": {
                "data_as_of": "2022-10-31 23:59",
                "last_updated": "2022-12-23 12:00",
                "next_update": "2023-01-31 12:00"
            },
            "metadata_lang": {
                "en": {
                    "methodology": "Lorem ipsum dolor sit amet, consectetur adipiscing elit, sed do eiusmod tempor incididunt ut labore et dolore magna aliqua. Ut enim ad minim veniam, quis nostrud exercitation ullamco laboris nisi ut aliquip ex ea commodo consequat.",
                    "caveat": "Lorem ipsum dolor sit amet, consectetur adipiscing elit, sed do eiusmod tempor incididunt ut labore et dolore magna aliqua. Ut enim ad minim veniam, quis nostrud exercitation ullamco laboris nisi ut aliquip ex ea commodo consequat."
                },
                "bm": {
                    "methodology": "Lorem ipsum dolor sit amet, consectetur adipiscing elit, sed do eiusmod tempor incididunt ut labore et dolore magna aliqua. Ut enim ad minim veniam, quis nostrud exercitation ullamco laboris nisi ut aliquip ex ea commodo consequat.",
                    "caveat": "Lorem ipsum dolor sit amet, consectetur adipiscing elit, sed do eiusmod tempor incididunt ut labore et dolore magna aliqua. Ut enim ad minim veniam, quis nostrud exercitation ullamco laboris nisi ut aliquip ex ea commodo consequat."
                }
            },
            "chart": {
                "chart_type": "TIMESERIES",
                "chart_filters": {
                    "SLICE_BY": []
                },
                "chart_variables": {
                    "parents": [],
                    "operation": "MEAN",
                    "format": {
                        "x": "date",
                        "y": "unemployed",
                        "line": ""
                    }
                }
            }
        },
        {
            "id": 4,
            "catalog_filters": {
                "frequency": "MONTHLY",
                "geographic": [
                    "NATIONAL"
                ],
                "start": "2010",
                "end": "2022",
                "data_source": [
                    "DOSM"
                ]
            },
            "metadata_neutral": {
                "data_as_of": "2022-10-31 23:59",
                "last_updated": "2022-12-23 12:00",
                "next_update": "2023-01-31 12:00"
            },
            "metadata_lang": {
                "en": {
                    "methodology": "Lorem ipsum dolor sit amet, consectetur adipiscing elit, sed do eiusmod tempor incididunt ut labore et dolore magna aliqua. Ut enim ad minim veniam, quis nostrud exercitation ullamco laboris nisi ut aliquip ex ea commodo consequat.",
                    "caveat": "Lorem ipsum dolor sit amet, consectetur adipiscing elit, sed do eiusmod tempor incididunt ut labore et dolore magna aliqua. Ut enim ad minim veniam, quis nostrud exercitation ullamco laboris nisi ut aliquip ex ea commodo consequat."
                },
                "bm": {
                    "methodology": "Lorem ipsum dolor sit amet, consectetur adipiscing elit, sed do eiusmod tempor incididunt ut labore et dolore magna aliqua. Ut enim ad minim veniam, quis nostrud exercitation ullamco laboris nisi ut aliquip ex ea commodo consequat.",
                    "caveat": "Lorem ipsum dolor sit amet, consectetur adipiscing elit, sed do eiusmod tempor incididunt ut labore et dolore magna aliqua. Ut enim ad minim veniam, quis nostrud exercitation ullamco laboris nisi ut aliquip ex ea commodo consequat."
                }
            },
            "chart": {
                "chart_type": "TIMESERIES",
                "chart_filters": {
                    "SLICE_BY": []
                },
                "chart_variables": {
                    "parents": [],
                    "operation": "MEAN",
                    "format": {
                        "x": "date",
                        "y": "outside",
                        "line": ""
                    }
                }
            }
        },
        {
            "id": 5,
            "catalog_filters": {
                "frequency": "MONTHLY",
                "geographic": [
                    "NATIONAL"
                ],
                "start": "2010",
                "end": "2022",
                "data_source": [
                    "DOSM"
                ]
            },
            "metadata_neutral": {
                "data_as_of": "2022-10-31 23:59",
                "last_updated": "2022-12-23 12:00",
                "next_update": "2023-01-31 12:00"
            },
            "metadata_lang": {
                "en": {
                    "methodology": "Lorem ipsum dolor sit amet, consectetur adipiscing elit, sed do eiusmod tempor incididunt ut labore et dolore magna aliqua. Ut enim ad minim veniam, quis nostrud exercitation ullamco laboris nisi ut aliquip ex ea commodo consequat.",
                    "caveat": "Lorem ipsum dolor sit amet, consectetur adipiscing elit, sed do eiusmod tempor incididunt ut labore et dolore magna aliqua. Ut enim ad minim veniam, quis nostrud exercitation ullamco laboris nisi ut aliquip ex ea commodo consequat."
                },
                "bm": {
                    "methodology": "Lorem ipsum dolor sit amet, consectetur adipiscing elit, sed do eiusmod tempor incididunt ut labore et dolore magna aliqua. Ut enim ad minim veniam, quis nostrud exercitation ullamco laboris nisi ut aliquip ex ea commodo consequat.",
                    "caveat": "Lorem ipsum dolor sit amet, consectetur adipiscing elit, sed do eiusmod tempor incididunt ut labore et dolore magna aliqua. Ut enim ad minim veniam, quis nostrud exercitation ullamco laboris nisi ut aliquip ex ea commodo consequat."
                }
            },
            "chart": {
                "chart_type": "TIMESERIES",
                "chart_filters": {
                    "SLICE_BY": []
                },
                "chart_variables": {
                    "parents": [],
                    "operation": "MEAN",
                    "format": {
                        "x": "date",
                        "y": "u_rate",
                        "line": ""
                    }
                }
            }
        },
        {
            "id": 6,
            "catalog_filters": {
                "frequency": "MONTHLY",
                "geographic": [
                    "NATIONAL"
                ],
                "start": "2010",
                "end": "2022",
                "data_source": [
                    "DOSM"
                ]
            },
            "metadata_neutral": {
                "data_as_of": "2022-10-31 23:59",
                "last_updated": "2022-12-23 12:00",
                "next_update": "2023-01-31 12:00"
            },
            "metadata_lang": {
                "en": {
                    "methodology": "Lorem ipsum dolor sit amet, consectetur adipiscing elit, sed do eiusmod tempor incididunt ut labore et dolore magna aliqua. Ut enim ad minim veniam, quis nostrud exercitation ullamco laboris nisi ut aliquip ex ea commodo consequat.",
                    "caveat": "Lorem ipsum dolor sit amet, consectetur adipiscing elit, sed do eiusmod tempor incididunt ut labore et dolore magna aliqua. Ut enim ad minim veniam, quis nostrud exercitation ullamco laboris nisi ut aliquip ex ea commodo consequat."
                },
                "bm": {
                    "methodology": "Lorem ipsum dolor sit amet, consectetur adipiscing elit, sed do eiusmod tempor incididunt ut labore et dolore magna aliqua. Ut enim ad minim veniam, quis nostrud exercitation ullamco laboris nisi ut aliquip ex ea commodo consequat.",
                    "caveat": "Lorem ipsum dolor sit amet, consectetur adipiscing elit, sed do eiusmod tempor incididunt ut labore et dolore magna aliqua. Ut enim ad minim veniam, quis nostrud exercitation ullamco laboris nisi ut aliquip ex ea commodo consequat."
                }
            },
            "chart": {
                "chart_type": "TIMESERIES",
                "chart_filters": {
                    "SLICE_BY": []
                },
                "chart_variables": {
                    "parents": [],
                    "operation": "MEAN",
                    "format": {
                        "x": "date",
                        "y": "p_rate",
                        "line": ""
                    }
                }
            }
        },
        {
            "id": 7,
            "catalog_filters": {
                "frequency": "MONTHLY",
                "geographic": [
                    "NATIONAL"
                ],
                "start": "2010",
                "end": "2022",
                "data_source": [
                    "DOSM"
                ]
            },
            "metadata_neutral": {
                "data_as_of": "2022-10-31 23:59",
                "last_updated": "2022-12-23 12:00",
                "next_update": "2023-01-31 12:00"
            },
            "metadata_lang": {
                "en": {
                    "methodology": "Lorem ipsum dolor sit amet, consectetur adipiscing elit, sed do eiusmod tempor incididunt ut labore et dolore magna aliqua. Ut enim ad minim veniam, quis nostrud exercitation ullamco laboris nisi ut aliquip ex ea commodo consequat.",
                    "caveat": "Lorem ipsum dolor sit amet, consectetur adipiscing elit, sed do eiusmod tempor incididunt ut labore et dolore magna aliqua. Ut enim ad minim veniam, quis nostrud exercitation ullamco laboris nisi ut aliquip ex ea commodo consequat."
                },
                "bm": {
                    "methodology": "Lorem ipsum dolor sit amet, consectetur adipiscing elit, sed do eiusmod tempor incididunt ut labore et dolore magna aliqua. Ut enim ad minim veniam, quis nostrud exercitation ullamco laboris nisi ut aliquip ex ea commodo consequat.",
                    "caveat": "Lorem ipsum dolor sit amet, consectetur adipiscing elit, sed do eiusmod tempor incididunt ut labore et dolore magna aliqua. Ut enim ad minim veniam, quis nostrud exercitation ullamco laboris nisi ut aliquip ex ea commodo consequat."
                }
            },
            "chart": {
                "chart_type": "TIMESERIES",
                "chart_filters": {
                    "SLICE_BY": []
                },
                "chart_variables": {
                    "parents": [],
                    "operation": "MEAN",
                    "format": {
                        "x": "date",
                        "y": "ep_ratio",
                        "line": ""
                    }
                }
            }
        },
        {
            "id": 8,
            "catalog_filters": {
                "frequency": "MONTHLY",
                "geographic": [
                    "NATIONAL"
                ],
                "start": "2010",
                "end": "2022",
                "data_source": [
                    "DOSM"
                ]
            },
            "metadata_neutral": {
                "data_as_of": "2022-10-31 23:59",
                "last_updated": "2022-12-23 12:00",
                "next_update": "2023-01-31 12:00"
            },
            "metadata_lang": {
                "en": {
                    "methodology": "Lorem ipsum dolor sit amet, consectetur adipiscing elit, sed do eiusmod tempor incididunt ut labore et dolore magna aliqua. Ut enim ad minim veniam, quis nostrud exercitation ullamco laboris nisi ut aliquip ex ea commodo consequat.",
                    "caveat": "Lorem ipsum dolor sit amet, consectetur adipiscing elit, sed do eiusmod tempor incididunt ut labore et dolore magna aliqua. Ut enim ad minim veniam, quis nostrud exercitation ullamco laboris nisi ut aliquip ex ea commodo consequat."
                },
                "bm": {
                    "methodology": "Lorem ipsum dolor sit amet, consectetur adipiscing elit, sed do eiusmod tempor incididunt ut labore et dolore magna aliqua. Ut enim ad minim veniam, quis nostrud exercitation ullamco laboris nisi ut aliquip ex ea commodo consequat.",
                    "caveat": "Lorem ipsum dolor sit amet, consectetur adipiscing elit, sed do eiusmod tempor incididunt ut labore et dolore magna aliqua. Ut enim ad minim veniam, quis nostrud exercitation ullamco laboris nisi ut aliquip ex ea commodo consequat."
                }
            },
            "chart": {
                "chart_type": "TIMESERIES",
                "chart_filters": {
                    "SLICE_BY": []
                },
                "chart_variables": {
                    "parents": [],
                    "operation": "MEAN",
                    "format": {
                        "x": "date",
                        "y": "lf_size_sa",
                        "line": ""
                    }
                }
            }
        },
        {
            "id": 9,
            "catalog_filters": {
                "frequency": "MONTHLY",
                "geographic": [
                    "NATIONAL"
                ],
                "start": "2010",
                "end": "2022",
                "data_source": [
                    "DOSM"
                ]
            },
            "metadata_neutral": {
                "data_as_of": "2022-10-31 23:59",
                "last_updated": "2022-12-23 12:00",
                "next_update": "2023-01-31 12:00"
            },
            "metadata_lang": {
                "en": {
                    "methodology": "Lorem ipsum dolor sit amet, consectetur adipiscing elit, sed do eiusmod tempor incididunt ut labore et dolore magna aliqua. Ut enim ad minim veniam, quis nostrud exercitation ullamco laboris nisi ut aliquip ex ea commodo consequat.",
                    "caveat": "Lorem ipsum dolor sit amet, consectetur adipiscing elit, sed do eiusmod tempor incididunt ut labore et dolore magna aliqua. Ut enim ad minim veniam, quis nostrud exercitation ullamco laboris nisi ut aliquip ex ea commodo consequat."
                },
                "bm": {
                    "methodology": "Lorem ipsum dolor sit amet, consectetur adipiscing elit, sed do eiusmod tempor incididunt ut labore et dolore magna aliqua. Ut enim ad minim veniam, quis nostrud exercitation ullamco laboris nisi ut aliquip ex ea commodo consequat.",
                    "caveat": "Lorem ipsum dolor sit amet, consectetur adipiscing elit, sed do eiusmod tempor incididunt ut labore et dolore magna aliqua. Ut enim ad minim veniam, quis nostrud exercitation ullamco laboris nisi ut aliquip ex ea commodo consequat."
                }
            },
            "chart": {
                "chart_type": "TIMESERIES",
                "chart_filters": {
                    "SLICE_BY": []
                },
                "chart_variables": {
                    "parents": [],
                    "operation": "MEAN",
                    "format": {
                        "x": "date",
                        "y": "employed_sa",
                        "line": ""
                    }
                }
            }
        },
        {
            "id": 10,
            "catalog_filters": {
                "frequency": "MONTHLY",
                "geographic": [
                    "NATIONAL"
                ],
                "start": "2010",
                "end": "2022",
                "data_source": [
                    "DOSM"
                ]
            },
            "metadata_neutral": {
                "data_as_of": "2022-10-31 23:59",
                "last_updated": "2022-12-23 12:00",
                "next_update": "2023-01-31 12:00"
            },
            "metadata_lang": {
                "en": {
                    "methodology": "Lorem ipsum dolor sit amet, consectetur adipiscing elit, sed do eiusmod tempor incididunt ut labore et dolore magna aliqua. Ut enim ad minim veniam, quis nostrud exercitation ullamco laboris nisi ut aliquip ex ea commodo consequat.",
                    "caveat": "Lorem ipsum dolor sit amet, consectetur adipiscing elit, sed do eiusmod tempor incididunt ut labore et dolore magna aliqua. Ut enim ad minim veniam, quis nostrud exercitation ullamco laboris nisi ut aliquip ex ea commodo consequat."
                },
                "bm": {
                    "methodology": "Lorem ipsum dolor sit amet, consectetur adipiscing elit, sed do eiusmod tempor incididunt ut labore et dolore magna aliqua. Ut enim ad minim veniam, quis nostrud exercitation ullamco laboris nisi ut aliquip ex ea commodo consequat.",
                    "caveat": "Lorem ipsum dolor sit amet, consectetur adipiscing elit, sed do eiusmod tempor incididunt ut labore et dolore magna aliqua. Ut enim ad minim veniam, quis nostrud exercitation ullamco laboris nisi ut aliquip ex ea commodo consequat."
                }
            },
            "chart": {
                "chart_type": "TIMESERIES",
                "chart_filters": {
                    "SLICE_BY": []
                },
                "chart_variables": {
                    "parents": [],
                    "operation": "MEAN",
                    "format": {
                        "x": "date",
                        "y": "unemployed_sa",
                        "line": ""
                    }
                }
            }
        },
        {
            "id": 11,
            "catalog_filters": {
                "frequency": "MONTHLY",
                "geographic": [
                    "NATIONAL"
                ],
                "start": "2010",
                "end": "2022",
                "data_source": [
                    "DOSM"
                ]
            },
            "metadata_neutral": {
                "data_as_of": "2022-10-31 23:59",
                "last_updated": "2022-12-23 12:00",
                "next_update": "2023-01-31 12:00"
            },
            "metadata_lang": {
                "en": {
                    "methodology": "Lorem ipsum dolor sit amet, consectetur adipiscing elit, sed do eiusmod tempor incididunt ut labore et dolore magna aliqua. Ut enim ad minim veniam, quis nostrud exercitation ullamco laboris nisi ut aliquip ex ea commodo consequat.",
                    "caveat": "Lorem ipsum dolor sit amet, consectetur adipiscing elit, sed do eiusmod tempor incididunt ut labore et dolore magna aliqua. Ut enim ad minim veniam, quis nostrud exercitation ullamco laboris nisi ut aliquip ex ea commodo consequat."
                },
                "bm": {
                    "methodology": "Lorem ipsum dolor sit amet, consectetur adipiscing elit, sed do eiusmod tempor incididunt ut labore et dolore magna aliqua. Ut enim ad minim veniam, quis nostrud exercitation ullamco laboris nisi ut aliquip ex ea commodo consequat.",
                    "caveat": "Lorem ipsum dolor sit amet, consectetur adipiscing elit, sed do eiusmod tempor incididunt ut labore et dolore magna aliqua. Ut enim ad minim veniam, quis nostrud exercitation ullamco laboris nisi ut aliquip ex ea commodo consequat."
                }
            },
            "chart": {
                "chart_type": "TIMESERIES",
                "chart_filters": {
                    "SLICE_BY": []
                },
                "chart_variables": {
                    "parents": [],
                    "operation": "MEAN",
                    "format": {
                        "x": "date",
                        "y": "u_rate_sa",
                        "line": ""
                    }
                }
            }
        },
        {
            "id": 12,
            "catalog_filters": {
                "frequency": "MONTHLY",
                "geographic": [
                    "NATIONAL"
                ],
                "start": "2010",
                "end": "2022",
                "data_source": [
                    "DOSM"
                ]
            },
            "metadata_neutral": {
                "data_as_of": "2022-10-31 23:59",
                "last_updated": "2022-12-23 12:00",
                "next_update": "2023-01-31 12:00"
            },
            "metadata_lang": {
                "en": {
                    "methodology": "Lorem ipsum dolor sit amet, consectetur adipiscing elit, sed do eiusmod tempor incididunt ut labore et dolore magna aliqua. Ut enim ad minim veniam, quis nostrud exercitation ullamco laboris nisi ut aliquip ex ea commodo consequat.",
                    "caveat": "Lorem ipsum dolor sit amet, consectetur adipiscing elit, sed do eiusmod tempor incididunt ut labore et dolore magna aliqua. Ut enim ad minim veniam, quis nostrud exercitation ullamco laboris nisi ut aliquip ex ea commodo consequat."
                },
                "bm": {
                    "methodology": "Lorem ipsum dolor sit amet, consectetur adipiscing elit, sed do eiusmod tempor incididunt ut labore et dolore magna aliqua. Ut enim ad minim veniam, quis nostrud exercitation ullamco laboris nisi ut aliquip ex ea commodo consequat.",
                    "caveat": "Lorem ipsum dolor sit amet, consectetur adipiscing elit, sed do eiusmod tempor incididunt ut labore et dolore magna aliqua. Ut enim ad minim veniam, quis nostrud exercitation ullamco laboris nisi ut aliquip ex ea commodo consequat."
                }
            },
            "chart": {
                "chart_type": "TIMESERIES",
                "chart_filters": {
                    "SLICE_BY": []
                },
                "chart_variables": {
                    "parents": [],
                    "operation": "MEAN",
                    "format": {
                        "x": "date",
                        "y": "p_rate_sa",
                        "line": ""
                    }
                }
            }
        },
        {
            "id": 13,
            "catalog_filters": {
                "frequency": "MONTHLY",
                "geographic": [
                    "NATIONAL"
                ],
                "start": "2016",
                "end": "2022",
                "data_source": [
                    "DOSM"
                ]
            },
            "metadata_neutral": {
                "data_as_of": "2022-10-31 23:59",
                "last_updated": "2022-12-23 12:00",
                "next_update": "2023-01-31 12:00"
            },
            "metadata_lang": {
                "en": {
                    "methodology": "Lorem ipsum dolor sit amet, consectetur adipiscing elit, sed do eiusmod tempor incididunt ut labore et dolore magna aliqua. Ut enim ad minim veniam, quis nostrud exercitation ullamco laboris nisi ut aliquip ex ea commodo consequat.",
                    "caveat": "Lorem ipsum dolor sit amet, consectetur adipiscing elit, sed do eiusmod tempor incididunt ut labore et dolore magna aliqua. Ut enim ad minim veniam, quis nostrud exercitation ullamco laboris nisi ut aliquip ex ea commodo consequat."
                },
                "bm": {
                    "methodology": "Lorem ipsum dolor sit amet, consectetur adipiscing elit, sed do eiusmod tempor incididunt ut labore et dolore magna aliqua. Ut enim ad minim veniam, quis nostrud exercitation ullamco laboris nisi ut aliquip ex ea commodo consequat.",
                    "caveat": "Lorem ipsum dolor sit amet, consectetur adipiscing elit, sed do eiusmod tempor incididunt ut labore et dolore magna aliqua. Ut enim ad minim veniam, quis nostrud exercitation ullamco laboris nisi ut aliquip ex ea commodo consequat."
                }
            },
            "chart": {
                "chart_type": "TIMESERIES",
                "chart_filters": {
                    "SLICE_BY": []
                },
                "chart_variables": {
                    "parents": [],
                    "operation": "MEAN",
                    "format": {
                        "x": "date",
                        "y": "unemployed_15_24",
                        "line": ""
                    }
                }
            }
        },
        {
            "id": 14,
            "catalog_filters": {
                "frequency": "MONTHLY",
                "geographic": [
                    "NATIONAL"
                ],
                "start": "2016",
                "end": "2022",
                "data_source": [
                    "DOSM"
                ]
            },
            "metadata_neutral": {
                "data_as_of": "2022-10-31 23:59",
                "last_updated": "2022-12-23 12:00",
                "next_update": "2023-01-31 12:00"
            },
            "metadata_lang": {
                "en": {
                    "methodology": "Lorem ipsum dolor sit amet, consectetur adipiscing elit, sed do eiusmod tempor incididunt ut labore et dolore magna aliqua. Ut enim ad minim veniam, quis nostrud exercitation ullamco laboris nisi ut aliquip ex ea commodo consequat.",
                    "caveat": "Lorem ipsum dolor sit amet, consectetur adipiscing elit, sed do eiusmod tempor incididunt ut labore et dolore magna aliqua. Ut enim ad minim veniam, quis nostrud exercitation ullamco laboris nisi ut aliquip ex ea commodo consequat."
                },
                "bm": {
                    "methodology": "Lorem ipsum dolor sit amet, consectetur adipiscing elit, sed do eiusmod tempor incididunt ut labore et dolore magna aliqua. Ut enim ad minim veniam, quis nostrud exercitation ullamco laboris nisi ut aliquip ex ea commodo consequat.",
                    "caveat": "Lorem ipsum dolor sit amet, consectetur adipiscing elit, sed do eiusmod tempor incididunt ut labore et dolore magna aliqua. Ut enim ad minim veniam, quis nostrud exercitation ullamco laboris nisi ut aliquip ex ea commodo consequat."
                }
            },
            "chart": {
                "chart_type": "TIMESERIES",
                "chart_filters": {
                    "SLICE_BY": []
                },
                "chart_variables": {
                    "parents": [],
                    "operation": "MEAN",
                    "format": {
                        "x": "date",
                        "y": "u_rate_15_24",
                        "line": ""
                    }
                }
            }
        },
        {
            "id": 15,
            "catalog_filters": {
                "frequency": "MONTHLY",
                "geographic": [
                    "NATIONAL"
                ],
                "start": "2016",
                "end": "2022",
                "data_source": [
                    "DOSM"
                ]
            },
            "metadata_neutral": {
                "data_as_of": "2022-10-31 23:59",
                "last_updated": "2022-12-23 12:00",
                "next_update": "2023-01-31 12:00"
            },
            "metadata_lang": {
                "en": {
                    "methodology": "Lorem ipsum dolor sit amet, consectetur adipiscing elit, sed do eiusmod tempor incididunt ut labore et dolore magna aliqua. Ut enim ad minim veniam, quis nostrud exercitation ullamco laboris nisi ut aliquip ex ea commodo consequat.",
                    "caveat": "Lorem ipsum dolor sit amet, consectetur adipiscing elit, sed do eiusmod tempor incididunt ut labore et dolore magna aliqua. Ut enim ad minim veniam, quis nostrud exercitation ullamco laboris nisi ut aliquip ex ea commodo consequat."
                },
                "bm": {
                    "methodology": "Lorem ipsum dolor sit amet, consectetur adipiscing elit, sed do eiusmod tempor incididunt ut labore et dolore magna aliqua. Ut enim ad minim veniam, quis nostrud exercitation ullamco laboris nisi ut aliquip ex ea commodo consequat.",
                    "caveat": "Lorem ipsum dolor sit amet, consectetur adipiscing elit, sed do eiusmod tempor incididunt ut labore et dolore magna aliqua. Ut enim ad minim veniam, quis nostrud exercitation ullamco laboris nisi ut aliquip ex ea commodo consequat."
                }
            },
            "chart": {
                "chart_type": "TIMESERIES",
                "chart_filters": {
                    "SLICE_BY": []
                },
                "chart_variables": {
                    "parents": [],
                    "operation": "MEAN",
                    "format": {
                        "x": "date",
                        "y": "unemployed_15_30",
                        "line": ""
                    }
                }
            }
        },
        {
            "id": 16,
            "catalog_filters": {
                "frequency": "MONTHLY",
                "geographic": [
                    "NATIONAL"
                ],
                "start": "2016",
                "end": "2022",
                "data_source": [
                    "DOSM"
                ]
            },
            "metadata_neutral": {
                "data_as_of": "2022-10-31 23:59",
                "last_updated": "2022-12-23 12:00",
                "next_update": "2023-01-31 12:00"
            },
            "metadata_lang": {
                "en": {
                    "methodology": "Lorem ipsum dolor sit amet, consectetur adipiscing elit, sed do eiusmod tempor incididunt ut labore et dolore magna aliqua. Ut enim ad minim veniam, quis nostrud exercitation ullamco laboris nisi ut aliquip ex ea commodo consequat.",
                    "caveat": "Lorem ipsum dolor sit amet, consectetur adipiscing elit, sed do eiusmod tempor incididunt ut labore et dolore magna aliqua. Ut enim ad minim veniam, quis nostrud exercitation ullamco laboris nisi ut aliquip ex ea commodo consequat."
                },
                "bm": {
                    "methodology": "Lorem ipsum dolor sit amet, consectetur adipiscing elit, sed do eiusmod tempor incididunt ut labore et dolore magna aliqua. Ut enim ad minim veniam, quis nostrud exercitation ullamco laboris nisi ut aliquip ex ea commodo consequat.",
                    "caveat": "Lorem ipsum dolor sit amet, consectetur adipiscing elit, sed do eiusmod tempor incididunt ut labore et dolore magna aliqua. Ut enim ad minim veniam, quis nostrud exercitation ullamco laboris nisi ut aliquip ex ea commodo consequat."
                }
            },
            "chart": {
                "chart_type": "TIMESERIES",
                "chart_filters": {
                    "SLICE_BY": []
                },
                "chart_variables": {
                    "parents": [],
                    "operation": "MEAN",
                    "format": {
                        "x": "date",
                        "y": "u_rate_15_30",
                        "line": ""
                    }
                }
            }
        },
        {
            "id": 17,
            "catalog_filters": {
                "frequency": "MONTHLY",
                "geographic": [
                    "NATIONAL"
                ],
                "start": "2016",
                "end": "2022",
                "data_source": [
                    "DOSM"
                ]
            },
            "metadata_neutral": {
                "data_as_of": "2022-10-31 23:59",
                "last_updated": "2022-12-23 12:00",
                "next_update": "2023-01-31 12:00"
            },
            "metadata_lang": {
                "en": {
                    "methodology": "Lorem ipsum dolor sit amet, consectetur adipiscing elit, sed do eiusmod tempor incididunt ut labore et dolore magna aliqua. Ut enim ad minim veniam, quis nostrud exercitation ullamco laboris nisi ut aliquip ex ea commodo consequat.",
                    "caveat": "Lorem ipsum dolor sit amet, consectetur adipiscing elit, sed do eiusmod tempor incididunt ut labore et dolore magna aliqua. Ut enim ad minim veniam, quis nostrud exercitation ullamco laboris nisi ut aliquip ex ea commodo consequat."
                },
                "bm": {
                    "methodology": "Lorem ipsum dolor sit amet, consectetur adipiscing elit, sed do eiusmod tempor incididunt ut labore et dolore magna aliqua. Ut enim ad minim veniam, quis nostrud exercitation ullamco laboris nisi ut aliquip ex ea commodo consequat.",
                    "caveat": "Lorem ipsum dolor sit amet, consectetur adipiscing elit, sed do eiusmod tempor incididunt ut labore et dolore magna aliqua. Ut enim ad minim veniam, quis nostrud exercitation ullamco laboris nisi ut aliquip ex ea commodo consequat."
                }
            },
            "chart": {
                "chart_type": "TIMESERIES",
                "chart_filters": {
                    "SLICE_BY": []
                },
                "chart_variables": {
                    "parents": [],
                    "operation": "MEAN",
                    "format": {
                        "x": "date",
                        "y": "employed_employer",
                        "line": ""
                    }
                }
            }
        },
        {
            "id": 18,
            "catalog_filters": {
                "frequency": "MONTHLY",
                "geographic": [
                    "NATIONAL"
                ],
                "start": "2016",
                "end": "2022",
                "data_source": [
                    "DOSM"
                ]
            },
            "metadata_neutral": {
                "data_as_of": "2022-10-31 23:59",
                "last_updated": "2022-12-23 12:00",
                "next_update": "2023-01-31 12:00"
            },
            "metadata_lang": {
                "en": {
                    "methodology": "Lorem ipsum dolor sit amet, consectetur adipiscing elit, sed do eiusmod tempor incididunt ut labore et dolore magna aliqua. Ut enim ad minim veniam, quis nostrud exercitation ullamco laboris nisi ut aliquip ex ea commodo consequat.",
                    "caveat": "Lorem ipsum dolor sit amet, consectetur adipiscing elit, sed do eiusmod tempor incididunt ut labore et dolore magna aliqua. Ut enim ad minim veniam, quis nostrud exercitation ullamco laboris nisi ut aliquip ex ea commodo consequat."
                },
                "bm": {
                    "methodology": "Lorem ipsum dolor sit amet, consectetur adipiscing elit, sed do eiusmod tempor incididunt ut labore et dolore magna aliqua. Ut enim ad minim veniam, quis nostrud exercitation ullamco laboris nisi ut aliquip ex ea commodo consequat.",
                    "caveat": "Lorem ipsum dolor sit amet, consectetur adipiscing elit, sed do eiusmod tempor incididunt ut labore et dolore magna aliqua. Ut enim ad minim veniam, quis nostrud exercitation ullamco laboris nisi ut aliquip ex ea commodo consequat."
                }
            },
            "chart": {
                "chart_type": "TIMESERIES",
                "chart_filters": {
                    "SLICE_BY": []
                },
                "chart_variables": {
                    "parents": [],
                    "operation": "MEAN",
                    "format": {
                        "x": "date",
                        "y": "employed_employee",
                        "line": ""
                    }
                }
            }
        },
        {
            "id": 19,
            "catalog_filters": {
                "frequency": "MONTHLY",
                "geographic": [
                    "NATIONAL"
                ],
                "start": "2016",
                "end": "2022",
                "data_source": [
                    "DOSM"
                ]
            },
            "metadata_neutral": {
                "data_as_of": "2022-10-31 23:59",
                "last_updated": "2022-12-23 12:00",
                "next_update": "2023-01-31 12:00"
            },
            "metadata_lang": {
                "en": {
                    "methodology": "Lorem ipsum dolor sit amet, consectetur adipiscing elit, sed do eiusmod tempor incididunt ut labore et dolore magna aliqua. Ut enim ad minim veniam, quis nostrud exercitation ullamco laboris nisi ut aliquip ex ea commodo consequat.",
                    "caveat": "Lorem ipsum dolor sit amet, consectetur adipiscing elit, sed do eiusmod tempor incididunt ut labore et dolore magna aliqua. Ut enim ad minim veniam, quis nostrud exercitation ullamco laboris nisi ut aliquip ex ea commodo consequat."
                },
                "bm": {
                    "methodology": "Lorem ipsum dolor sit amet, consectetur adipiscing elit, sed do eiusmod tempor incididunt ut labore et dolore magna aliqua. Ut enim ad minim veniam, quis nostrud exercitation ullamco laboris nisi ut aliquip ex ea commodo consequat.",
                    "caveat": "Lorem ipsum dolor sit amet, consectetur adipiscing elit, sed do eiusmod tempor incididunt ut labore et dolore magna aliqua. Ut enim ad minim veniam, quis nostrud exercitation ullamco laboris nisi ut aliquip ex ea commodo consequat."
                }
            },
            "chart": {
                "chart_type": "TIMESERIES",
                "chart_filters": {
                    "SLICE_BY": []
                },
                "chart_variables": {
                    "parents": [],
                    "operation": "MEAN",
                    "format": {
                        "x": "date",
                        "y": "employed_ownaccount",
                        "line": ""
                    }
                }
            }
        },
        {
            "id": 20,
            "catalog_filters": {
                "frequency": "MONTHLY",
                "geographic": [
                    "NATIONAL"
                ],
                "start": "2016",
                "end": "2022",
                "data_source": [
                    "DOSM"
                ]
            },
            "metadata_neutral": {
                "data_as_of": "2022-10-31 23:59",
                "last_updated": "2022-12-23 12:00",
                "next_update": "2023-01-31 12:00"
            },
            "metadata_lang": {
                "en": {
                    "methodology": "Lorem ipsum dolor sit amet, consectetur adipiscing elit, sed do eiusmod tempor incididunt ut labore et dolore magna aliqua. Ut enim ad minim veniam, quis nostrud exercitation ullamco laboris nisi ut aliquip ex ea commodo consequat.",
                    "caveat": "Lorem ipsum dolor sit amet, consectetur adipiscing elit, sed do eiusmod tempor incididunt ut labore et dolore magna aliqua. Ut enim ad minim veniam, quis nostrud exercitation ullamco laboris nisi ut aliquip ex ea commodo consequat."
                },
                "bm": {
                    "methodology": "Lorem ipsum dolor sit amet, consectetur adipiscing elit, sed do eiusmod tempor incididunt ut labore et dolore magna aliqua. Ut enim ad minim veniam, quis nostrud exercitation ullamco laboris nisi ut aliquip ex ea commodo consequat.",
                    "caveat": "Lorem ipsum dolor sit amet, consectetur adipiscing elit, sed do eiusmod tempor incididunt ut labore et dolore magna aliqua. Ut enim ad minim veniam, quis nostrud exercitation ullamco laboris nisi ut aliquip ex ea commodo consequat."
                }
            },
            "chart": {
                "chart_type": "TIMESERIES",
                "chart_filters": {
                    "SLICE_BY": []
                },
                "chart_variables": {
                    "parents": [],
                    "operation": "MEAN",
                    "format": {
                        "x": "date",
                        "y": "employed_unpaidfamily",
                        "line": ""
                    }
                }
            }
        }
    ]
}